[
  {
    "id": "se137",
    "name": "Sveriges Radio P4 Värmland",
    "streamUrl": "https://ljud1-cdn.sr.se/lc/p4vrml.m3u8",
    "imageUrl": "https://static.mytuner.mobi/media/radios-150px/468/sveriges-radio-p4-sjuharad.cacc1f69.jpg",
    "genre": "genre_info",
    "country": "country_sweden"
  },
  {
    "id": "se138",
    "name": "Sveriges Radio P4 Jämtland",
    "streamUrl": "https://edge2.sr.se/p4jmtl-mp3-96",
    "imageUrl": "https://static.mytuner.mobi/media/radios-150px/468/sveriges-radio-p4-sjuharad.cacc1f69.jpg",
    "genre": "genre_info",
    "country": "country_sweden"
  },
  {
    "id": "se139",
    "name": "Sveriges Radio P4 Dalarna",
    "streamUrl": "https://ljud1-cdn.sr.se/lc/p4dala.m3u8",
    "imageUrl": "https://static.mytuner.mobi/media/radios-150px/468/sveriges-radio-p4-sjuharad.cacc1f69.jpg",
    "genre": "genre_info",
    "country": "country_sweden"
  },
  {
    "id": "se140",
    "name": "Sveriges Radio P4 Halland",
    "streamUrl": "https://ljud1-cdn.sr.se/lc/p4hall.m3u8",
    "imageUrl": "https://static.mytuner.mobi/media/radios-150px/468/sveriges-radio-p4-sjuharad.cacc1f69.jpg",
    "genre": "genre_info",
    "country": "country_sweden"
  },
  {
    "id": "se141",
    "name": "Sveriges Radio P4 Östergötland",
    "streamUrl": "https://edge2.sr.se/p4ostg-mp3-96",
    "imageUrl": "https://static.mytuner.mobi/media/radios-150px/468/sveriges-radio-p4-sjuharad.cacc1f69.jpg",
    "genre": "genre_info",
    "country": "country_sweden"
  },
  {
    "id": "se142",
    "name": "Sveriges Radio P4 Västmanland",
    "streamUrl": "https://edge2.sr.se/p4vstm-mp3-96",
    "imageUrl": "https://static.mytuner.mobi/media/radios-150px/468/sveriges-radio-p4-sjuharad.cacc1f69.jpg",
    "genre": "genre_info",
    "country": "country_sweden"
  },
  {
    "id": "se144",
    "name": "Sveriges Radio P2 Musik",
    "streamUrl": "https://ljud1-cdn.sr.se/lc/p2.m3u8",
    "imageUrl": "https://static.mytuner.mobi/media/radios-150px/564/sveriges-radio-p2-klassiskt.aeb2a165.jpg",
    "genre": "genre_clasic",
    "country": "country_sweden"
  },
  {
    "id": "se145",
    "name": "Gold 102.4",
    "streamUrl": "http://goldfm.nu:8082/goldfm_mp3",
    "imageUrl": "https://static.mytuner.mobi/media/radios-150px/454/gold-1024.58c22f13.jpg",
    "genre": "genre_retro",
    "country": "country_sweden"
  },
  {
    "id": "se146",
    "name": "Guldkanalen Helsingborg",
    "streamUrl": "http://stream.dbmedia.se/gkhbg96",
    "imageUrl": "https://static.mytuner.mobi/media/radios-150px/313/1026-guldkanalen.2051b576.png",
    "genre": "genre_retro",
    "country": "country_sweden"
  },
  {
    "id": "se147",
    "name": "BozRadio",
    "streamUrl": "http://das-edge14-live365-dal02.cdnstream.com/a80252",
    "imageUrl": "https://image.live365.com/download/78b6f4e8-32a3-4cb5-b373-fc02a7d07d0c.png/400/image.webp",
    "genre": "genre_pop",
    "country": "country_sweden"
  },
  {
    "id": "ie2",
    "name": "Spin South West",
    "streamUrl": "https://stream.audioxi.com/SW",
    "imageUrl": "https://cdn.onlineradiobox.com/img/l/0/7710.v9.png",
    "genre": "genre_hits",
    "country": "country_ireland"
  },
  {
    "id": "ie3",
    "name": "FM 104",
    "streamUrl": "https://live.onic.ie/stream-fm104",
    "imageUrl": "https://irishradiolive.com/public/uploads/radio_img/fm104/play_250_250.webp",
    "genre": "genre_hits",
    "country": "country_ireland"
  },
  {
    "id": "ie6",
    "name": "Noughty Beats",
    "streamUrl": "https://stream.audioxi.com/NBEATSAAC",
    "imageUrl": "https://cdn.onlineradiobox.com/img/l/7/87167.v3.png",
    "genre": "genre_90s",
    "country": "country_ireland"
  },
  {
    "id": "ie10",
    "name": "Global Irish Radio",
    "streamUrl": "https://s3.radio.co/s05b500bb8/listen",
    "imageUrl": "https://cdn.onlineradiobox.com/img/l/8/99468.v1.png",
    "genre": "genre_folk",
    "country": "country_ireland"
  },
  {
    "id": "ie11",
    "name": "Today 80s",
    "streamUrl": "http://edge3.audioxi.com/T80",
    "imageUrl": "https://cdn.onlineradiobox.com/img/l/6/95756.v2.png",
    "genre": "genre_retro",
    "country": "country_ireland"
  },
  {
    "id": "ie14",
    "name": "Our Voice FM",
    "streamUrl": "https://s3.radio.co/s1a0d3a043/listen",
    "imageUrl": "https://zeno.fm/_ipx/_/https://images.zeno.fm/jH8w99qP1Dfod-gcCNKpocJk5N8-uSLjOogBwvyY89E/rs:fill:288:288/g:ce:0:0/aHR0cHM6Ly9wcm94eS56ZW5vLmZtL2NvbnRlbnQvc3RhdGlvbnMvODkzNDlhZTItYjJlZi00YWI3LTgwM2MtNDg2Mjc4MGUyMzg5L2ltYWdlLz91PTE3MTM4NzMyMzcwMDA.webp",
    "genre": "genre_pop",
    "country": "country_ireland"
  },
  {
    "id": "ie16",
    "name": "Minimal & Deep-tech on MixLive.ie",
    "streamUrl": "https://strw3.openstream.co/574",
    "imageUrl": "https://cdn.onlineradiobox.com/img/l/3/119343.v9.png",
    "genre": "genre_dance",
    "country": "country_ireland"
  },
  {
    "id": "ie17",
    "name": "Classic Hits Radio",
    "streamUrl": "https://edge.audioxi.com/CLASSIC",
    "imageUrl": "https://cdn.onlineradiobox.com/img/l/3/7073.v9.png",
    "genre": "genre_clasic",
    "country": "country_ireland"
  },
  {
    "id": "ie21",
    "name": "Trance Illusion on MixLive.ie",
    "streamUrl": "https://strw3.openstream.co/941",
    "imageUrl": "https://cdn.onlineradiobox.com/img/l/0/86830.v7.png",
    "genre": "genre_dance",
    "country": "country_ireland"
  },
  {
    "id": "ie22",
    "name": "RTÉ Lyric FM",
    "streamUrl": "https://27913.live.streamtheworld.com/RTE_LYRIC_FMAACLC/HLS/playlist.m3u8",
    "imageUrl": "https://cdn.onlineradiobox.com/img/l/5/7145.v20.png",
    "genre": "genre_clasic",
    "country": "country_ireland"
  },
  {
    "id": "ie24",
    "name": "The Sound of Ireland",
    "streamUrl": "https://christmasfm.cdnstream1.com/2548_128.mp3",
    "imageUrl": "https://cdn.onlineradiobox.com/img/l/1/74821.v9.png",
    "genre": "genre_pop",
    "country": "country_ireland"
  },
  {
    "id": "ie25",
    "name": "PlanetRadio.ie Country Hits",
    "streamUrl": "https://media.planetradio.ie/radio/8010/Country",
    "imageUrl": "https://cdn.onlineradiobox.com/img/l/2/90552.v2.png",
    "genre": "genre_folk",
    "country": "country_ireland"
  },
  {
    "id": "ie26",
    "name": "Today 90s",
    "streamUrl": "http://edge3.audioxi.com/T90AAC",
    "imageUrl": "https://cdn.onlineradiobox.com/img/l/6/7216.v10.png",
    "genre": "genre_90s",
    "country": "country_ireland"
  },
  {
    "id": "ie28",
    "name": "Radio Zodiac Ireland",
    "streamUrl": "https://listen.radioking.com/radio/124966/stream/164656",
    "imageUrl": "https://cdn.onlineradiobox.com/img/logo/5/145065.png",
    "genre": "genre_pop",
    "country": "country_ireland"
  },
  {
    "id": "ie31",
    "name": "Deep Planet on MixLive.ie",
    "streamUrl": "https://strw3.openstream.co/947",
    "imageUrl": "https://cdn.onlineradiobox.com/img/l/7/86847.v7.png",
    "genre": "genre_dance",
    "country": "country_ireland"
  },
  {
    "id": "ie32",
    "name": "iRadio Old Skool",
    "streamUrl": "https://stream.audioxi.com/IROSkool",
    "imageUrl": "https://cdn.onlineradiobox.com/img/l/1/7131.v7.png",
    "genre": "genre_retro",
    "country": "country_ireland"
  },
  {
    "id": "ie33",
    "name": "Cork Music Station",
    "streamUrl": "https://streamer.radio.co/s1a04f8902/listen",
    "imageUrl": "https://zeno.fm/_ipx/_/https://images.zeno.fm/Y8fVnNNPEXeBJQtAnvH9MHfdjac4zsCEiJj0TeWWrUs/rs:fill:288:288/g:ce:0:0/aHR0cHM6Ly9wcm94eS56ZW5vLmZtL2NvbnRlbnQvc3RhdGlvbnMvMzVjYmQyMzAtODM1Yy00ZDljLWEyNDItOTE3Yjg3NzhkYWU4L2ltYWdlLz91PTE3MTM5Mzc3MDkwMDA.webp",
    "genre": "genre_pop",
    "country": "country_ireland"
  },
  {
    "id": "ie35",
    "name": "Raidio Na Life",
    "streamUrl": "http://beryl.streamguys.com:5010/live",
    "imageUrl": "https://cdn.onlineradiobox.com/img/l/3/7143.v5.png",
    "genre": "genre_folk",
    "country": "country_ireland"
  },
  {
    "id": "ie37",
    "name": "Wired FM",
    "streamUrl": "https://s2.radio.co/sf0986595a/listen",
    "imageUrl": "https://cdn.onlineradiobox.com/img/l/1/7911.v6.png",
    "genre": "genre_hits",
    "country": "country_ireland"
  },
  {
    "id": "ie38",
    "name": "East Coast FM",
    "streamUrl": "https://live-bauerie.sharp-stream.com/EASTCOAST",
    "imageUrl": "https://cdn.onlineradiobox.com/img/l/7/7107.v4.png",
    "genre": "genre_pop",
    "country": "country_ireland"
  },
  {
    "id": "ie39",
    "name": "Minimal & Techno on MixLive.ie",
    "streamUrl": "https://strw3.openstream.co/940",
    "imageUrl": "https://cdn.onlineradiobox.com/img/l/9/86829.v6.png",
    "genre": "genre_dance",
    "country": "country_ireland"
  },
  {
    "id": "ie41",
    "name": "Live Ireland Channel 1",
    "streamUrl": "http://192.111.140.11:8058/stream",
    "imageUrl": "https://cdn.onlineradiobox.com/img/l/0/7270.v5.png",
    "genre": "genre_pop",
    "country": "country_ireland"
  },
  {
    "id": "ie43",
    "name": "Highland Radio",
    "streamUrl": "https://edge.audioxi.com/HIGHLAND",
    "imageUrl": "https://cdn.onlineradiobox.com/img/l/9/7699.v6.png",
    "genre": "genre_pop",
    "country": "country_ireland"
  },
  {
    "id": "ie44",
    "name": "Today FM",
    "streamUrl": "https://stream.audioxi.com/TD",
    "imageUrl": "https://cdn.onlineradiobox.com/img/l/6/7216.v10.png",
    "genre": "genre_hits",
    "country": "country_ireland"
  },
  {
    "id": "ie45",
    "name": "Ambient Lounge on MixLive.ie",
    "streamUrl": "https://strw3.openstream.co/2348",
    "imageUrl": "https://cdn.onlineradiobox.com/img/l/8/86818.v13.png",
    "genre": "genre_dance",
    "country": "country_ireland"
  },
  {
    "id": "ie46",
    "name": "Northern Sound",
    "streamUrl": "https://edge.audioxi.com/NORTHERNSOUND",
    "imageUrl": "https://cdn.onlineradiobox.com/img/l/0/7720.v5.png",
    "genre": "genre_news",
    "country": "country_ireland"
  },
  {
    "id": "ie47",
    "name": "OTB AM Off the Ball",
    "streamUrl": "https://stream.audioxi.com/OTB",
    "imageUrl": "https://www.radio.net/175/otb-am-off-the-ball.png?version=b9898f41d076f428952677c3c50e4d0f03c74320",
    "genre": "genre_news",
    "country": "country_ireland"
  },
  {
    "id": "ie48",
    "name": "Freedom FM",
    "streamUrl": "https://edge3.audioxi.com/FREEDOMFMAAC",
    "imageUrl": "https://cdn.onlineradiobox.com/img/l/2/90422.v8.png",
    "genre": "genre_pop",
    "country": "country_ireland"
  },
  {
    "id": "ie50",
    "name": "Radio Nova",
    "streamUrl": "http://edge2.audioxi.com/NOVA",
    "imageUrl": "https://cdn.onlineradiobox.com/img/l/2/7142.v11.png",
    "genre": "genre_pop",
    "country": "country_ireland"
  },
  {
    "id": "ie51",
    "name": "Galway Bay FM",
    "streamUrl": "https://wg.cdn.tibus.net/galwaybay.mp3",
    "imageUrl": "https://cdn.onlineradiobox.com/img/l/3/7633.v6.png",
    "genre": "genre_pop",
    "country": "country_ireland"
  },
  {
    "id": "ie52",
    "name": "Greatest Hits",
    "streamUrl": "https://c16.radioboss.fm:18267/stream",
    "imageUrl": "https://cdn.onlineradiobox.com/img/l/1/83251.v24.png",
    "genre": "genre_retro",
    "country": "country_ireland"
  },
  {
    "id": "ie55",
    "name": "Solid Gold Radio Ireland 3",
    "streamUrl": "https://az10.yesstreaming.net:8300/radio.mp3",
    "imageUrl": "https://cdn.onlineradiobox.com/img/l/1/87021.v11.png",
    "genre": "genre_retro",
    "country": "country_ireland"
  },
  {
    "id": "ie56",
    "name": "Sunshine Soul",
    "streamUrl": "https://live-bauerie.sharp-stream.com/SSOULAAC",
    "imageUrl": "https://cdn.onlineradiobox.com/img/l/1/73141.v14.png",
    "genre": "genre_relax",
    "country": "country_ireland"
  },
  {
    "id": "ie57",
    "name": "Raidió Corca Baiscinn",
    "streamUrl": "http://178.33.135.245:3074/stream",
    "imageUrl": "https://cdn.onlineradiobox.com/img/l/0/7640.v6.png",
    "genre": "genre_pop",
    "country": "country_ireland"
  },
  {
    "id": "ie58",
    "name": "Psybient Sunset on MixLive.ie",
    "streamUrl": "https://strw3.openstream.co/932",
    "imageUrl": "https://cdn.onlineradiobox.com/img/l/0/86820.v8.png",
    "genre": "genre_dance",
    "country": "country_ireland"
  },
  {
    "id": "ie59",
    "name": "Open-Stage on MixLive.ie",
    "streamUrl": "https://strw3.openstream.co/957",
    "imageUrl": "https://cdn.onlineradiobox.com/img/l/0/86850.v7.png",
    "genre": "genre_dance",
    "country": "country_ireland"
  },
  {
    "id": "ie60",
    "name": "RosFM 94.6",
    "streamUrl": "https://fra-ranger01.dedicateware.com:2020/stream/rosfm946/stream",
    "imageUrl": "https://static2.mytuner.mobi/media/tvos_radios/yam47wqfgbrc.png",
    "genre": "genre_pop",
    "country": "country_ireland"
  },
  {
    "id": "ie62",
    "name": "Sunshine 106.8 FM",
    "streamUrl": "https://25553.live.streamtheworld.com/SUNSHINE_106_8.mp3?_=112251",
    "imageUrl": "https://cdn.onlineradiobox.com/img/l/2/7212.v11.png",
    "genre": "genre_pop",
    "country": "country_ireland"
  },
  {
    "id": "ie63",
    "name": "Cork's Red FM",
    "streamUrl": "https://edge.audioxi.com/RED",
    "imageUrl": "https://cdn.onlineradiobox.com/img/l/4/7654.v8.png",
    "genre": "genre_hits",
    "country": "country_ireland"
  },
  {
    "id": "ie64",
    "name": "Solid Gold Radio Ireland 2",
    "streamUrl": "https://az10.yesstreaming.net:8160/radio.mp3",
    "imageUrl": "https://cdn.onlineradiobox.com/img/l/6/103516.v10.png",
    "genre": "genre_retro",
    "country": "country_ireland"
  },
  {
    "id": "ie65",
    "name": "The 90s Network",
    "streamUrl": "http://uk1.streamingpulse.com:7020/stream",
    "imageUrl": "https://cdn.onlineradiobox.com/img/l/1/7441.v12.png",
    "genre": "genre_90s",
    "country": "country_ireland"
  },
  {
    "id": "ie66",
    "name": "Christmas FM",
    "streamUrl": "https://christmasfm.cdnstream1.com/2547_128.mp3",
    "imageUrl": "https://cdn.onlineradiobox.com/img/l/8/7938.v12.png",
    "genre": "genre_pop",
    "country": "country_ireland"
  },
  {
    "id": "ie67",
    "name": "NewsTalk 106-108",
    "streamUrl": "https://edge.audioxi.com/NT",
    "imageUrl": "https://cdn.onlineradiobox.com/img/l/7/7137.v9.png",
    "genre": "genre_news",
    "country": "country_ireland"
  },
  {
    "id": "ie68",
    "name": "Chillout Essentials on MixLive.ie",
    "streamUrl": "https://strw3.openstream.co/931",
    "imageUrl": "https://cdn.onlineradiobox.com/img/l/9/86819.v8.png",
    "genre": "genre_dance",
    "country": "country_ireland"
  },
  {
    "id": "ie70",
    "name": "PlanetRadio.ie",
    "streamUrl": "https://media.planetradio.ie/radio/8000/OnAir",
    "imageUrl": "https://cdn.onlineradiobox.com/img/l/4/90504.v10.png",
    "genre": "genre_pop",
    "country": "country_ireland"
  },
  {
    "id": "ie71",
    "name": "Christmas FM Classical",
    "streamUrl": "https://christmasfm.cdnstream1.com/2549_64.aac",
    "imageUrl": "https://cdn.onlineradiobox.com/img/l/2/74822.v12.png",
    "genre": "genre_clasic",
    "country": "country_ireland"
  },
  {
    "id": "ie72",
    "name": "Today XM",
    "streamUrl": "https://stream.audioxi.com/XMAAC",
    "imageUrl": "https://cdn.onlineradiobox.com/img/l/6/7216.v10.png",
    "genre": "genre_pop",
    "country": "country_ireland"
  },
  {
    "id": "ie73",
    "name": "South East Radio",
    "streamUrl": "https://edge4.audioxi.com/SOUTHEAST",
    "imageUrl": "https://cdn.onlineradiobox.com/img/l/2/7812.v5.png",
    "genre": "genre_pop",
    "country": "country_ireland"
  },
  {
    "id": "ie74",
    "name": "Finn Valley FM",
    "streamUrl": "http://visual.shoutca.st/stream/finnvalleyfm",
    "imageUrl": "https://static2.mytuner.mobi/media/tvos_radios/ad2lj4n8mypu.jpg",
    "genre": "genre_pop",
    "country": "country_ireland"
  },
  {
    "id": "ie75",
    "name": "Beat 102 103",
    "streamUrl": "https://stream.audioxi.com/BEATAAC",
    "imageUrl": "https://cdn.onlineradiobox.com/img/l/4/7794.v7.png",
    "genre": "genre_hits",
    "country": "country_ireland"
  },
  {
    "id": "ie76",
    "name": "Bass Station DnB on MixLive.ie",
    "streamUrl": "https://strw3.openstream.co/933",
    "imageUrl": "https://cdn.onlineradiobox.com/img/l/6/86826.v12.png",
    "genre": "genre_dance",
    "country": "country_ireland"
  },
  {
    "id": "ie77",
    "name": "Decades Radio Dublin",
    "streamUrl": "https://my2.radiolize.com/radio/8150/radio.mp3",
    "imageUrl": "https://static2.mytuner.mobi/media/tvos_radios/hby9gsldtxzv.jpg",
    "genre": "genre_retro",
    "country": "country_ireland"
  },
  {
    "id": "ie78",
    "name": "RTÉ Raidió Na Gaeltachta",
    "streamUrl": "http://28993.live.streamtheworld.com/RTE_RAIDIO_NA_GAELTACHTA.mp3",
    "imageUrl": "https://cdn.onlineradiobox.com/img/l/9/7259.v12.png",
    "genre": "genre_folk",
    "country": "country_ireland"
  },
  {
    "id": "ie80",
    "name": "RTÉ 2FM",
    "streamUrl": "http://icecast2.rte.ie/ie2fm",
    "imageUrl": "https://cdn.onlineradiobox.com/img/l/4/7144.v18.png",
    "genre": "genre_hits",
    "country": "country_ireland"
  },
  {
    "id": "ie81",
    "name": "All Gold Radio",
    "streamUrl": "https://centova1.cheapshoutcast.com/proxy/paul",
    "imageUrl": "https://cdn.onlineradiobox.com/img/l/7/8107.v12.png",
    "genre": "genre_retro",
    "country": "country_ireland"
  },
  {
    "id": "ie82",
    "name": "Lockdown Live Radio",
    "streamUrl": "http://studio24.radiolize.com:8050/radio.mp3",
    "imageUrl": "https://cdn.onlineradiobox.com/img/l/2/88372.v8.png",
    "genre": "genre_pop",
    "country": "country_ireland"
  },
  {
    "id": "ie83",
    "name": "Solid Gold Radio Ireland",
    "streamUrl": "https://az10.yesstreaming.net:8150/radio.mp3",
    "imageUrl": "https://cdn.onlineradiobox.com/img/l/5/83035.v10.png",
    "genre": "genre_retro",
    "country": "country_ireland"
  },
  {
    "id": "ie84",
    "name": "Siamsa",
    "streamUrl": "https://cast02.siamsa.ie/radio/8000/radio.mp3",
    "imageUrl": "https://cdn.onlineradiobox.com/img/l/4/83584.v5.png",
    "genre": "genre_folk",
    "country": "country_ireland"
  },
  {
    "id": "ie85",
    "name": "Spin 103.8 FM",
    "streamUrl": "https://edge.audioxi.com/SP",
    "imageUrl": "https://cdn.onlineradiobox.com/img/l/0/7190.v8.png",
    "genre": "genre_hits",
    "country": "country_ireland"
  },
  {
    "id": "ie86",
    "name": "Progressive & Tech-house on MixLive.ie",
    "streamUrl": "https://strw3.openstream.co/939",
    "imageUrl": "https://cdn.onlineradiobox.com/img/l/8/86828.v7.png",
    "genre": "genre_dance",
    "country": "country_ireland"
  },
  {
    "id": "ie87",
    "name": "LMFM Country Express",
    "streamUrl": "https://live.onic.ie/stream-country",
    "imageUrl": "https://cdn.onlineradiobox.com/img/l/1/7661.v10.png",
    "genre": "genre_folk",
    "country": "country_ireland"
  },
  {
    "id": "ie88",
    "name": "Midwest Radio FM",
    "streamUrl": "http://edge-audio-03-gos2.sharp-stream.com/midwestfmie.mp3",
    "imageUrl": "https://cdn.onlineradiobox.com/img/l/3/8153.v11.png",
    "genre": "genre_pop",
    "country": "country_ireland"
  },
  {
    "id": "ie90",
    "name": "Radio Kerry",
    "streamUrl": "https://edge.audioxi.com/KERRY",
    "imageUrl": "https://cdn.onlineradiobox.com/img/l/5/7745.v9.png",
    "genre": "genre_pop",
    "country": "country_ireland"
  },
  {
    "id": "ie91",
    "name": "Ocean FM",
    "streamUrl": "https://25533.live.streamtheworld.com/OCEAN_FM_SLIGO.mp3",
    "imageUrl": "https://cdn.onlineradiobox.com/img/l/7/7597.v18.png",
    "genre": "genre_pop",
    "country": "country_ireland"
  },
  {
    "id": "ie92",
    "name": "Harmony",
    "streamUrl": "http://173.208.177.90:13410/;",
    "imageUrl": "https://cdn.onlineradiobox.com/img/l/5/79555.v7.png",
    "genre": "genre_relax",
    "country": "country_ireland"
  },
  {
    "id": "ie93",
    "name": "WLR FM",
    "streamUrl": "https://25453.live.streamtheworld.com/WLR_FM.mp3?dist=onlineradiobox",
    "imageUrl": "https://cdn.onlineradiobox.com/img/l/9/7779.v11.png",
    "genre": "genre_pop",
    "country": "country_ireland"
  },
  {
    "id": "ie96",
    "name": "8Radio.com",
    "streamUrl": "https://edge4.audioxi.com/8RADIO",
    "imageUrl": "https://cdn.onlineradiobox.com/img/l/8/7018.v7.png",
    "genre": "genre_rock",
    "country": "country_ireland"
  },
  {
    "id": "ie97",
    "name": "Carlow FM",
    "streamUrl": "https://s21.myradiostream.com/:14706/listen.mp3",
    "imageUrl": "https://cdn.onlineradiobox.com/img/l/6/103986.v2.png",
    "genre": "genre_pop",
    "country": "country_ireland"
  },
  {
    "id": "ie98",
    "name": "Absolute Irish",
    "streamUrl": "https://29103.live.streamtheworld.com/ABSOLUTE_IRELAND.mp3",
    "imageUrl": "https://cdn.onlineradiobox.com/img/l/8/73968.v10.png",
    "genre": "genre_folk",
    "country": "country_ireland"
  },
  {
    "id": "ie99",
    "name": "Radio Shannonside",
    "streamUrl": "https://edge.audioxi.com/SHANNONSIDE",
    "imageUrl": "https://cdn.onlineradiobox.com/img/l/5/8015.v8.png",
    "genre": "genre_pop",
    "country": "country_ireland"
  },
  {
    "id": "ie100",
    "name": "House & Techno Classics on MixLive.ie",
    "streamUrl": "https://strw3.openstream.co/938",
    "imageUrl": "https://cdn.onlineradiobox.com/img/l/7/86827.v6.png",
    "genre": "genre_clasic",
    "country": "country_ireland"
  },
  {
    "id": "ie101",
    "name": "Submit Promo on MixLive.ie",
    "streamUrl": "https://strw3.openstream.co/944",
    "imageUrl": "https://cdn.onlineradiobox.com/img/l/5/86835.v6.png",
    "genre": "genre_dance",
    "country": "country_ireland"
  },
  {
    "id": "ie102",
    "name": "Clare FM",
    "streamUrl": "https://22653.live.streamtheworld.com/CLARE_FM.mp3",
    "imageUrl": "https://cdn.onlineradiobox.com/img/l/1/8031.v12.png",
    "genre": "genre_pop",
    "country": "country_ireland"
  },
  {
    "id": "ie103",
    "name": "98FM",
    "streamUrl": "https://edge2.audioxi.com/98",
    "imageUrl": "https://cdn.onlineradiobox.com/img/l/2/7072.v10.png",
    "genre": "genre_hits",
    "country": "country_ireland"
  },
  {
    "id": "ie104",
    "name": "Liffey Sound FM 96.4",
    "streamUrl": "http://stream.liffeysoundfm.ie:8000/listen.pls.mp3",
    "imageUrl": "https://cdn.onlineradiobox.com/img/l/3/7913.v7.png",
    "genre": "genre_pop",
    "country": "country_ireland"
  },
  {
    "id": "ie107",
    "name": "RTÉ Radio 1",
    "streamUrl": "https://25283.live.streamtheworld.com/RTE_1_INTAACLC/HLS/playlist.m3u8",
    "imageUrl": "https://cdn.onlineradiobox.com/img/l/6/7146.v20.png",
    "genre": "genre_pop",
    "country": "country_ireland"
  },
  {
    "id": "ie108",
    "name": "RTÉ Gold",
    "streamUrl": "https://27953.live.streamtheworld.com/RTE_GOLDAACLC/HLS/playlist.m3u8",
    "imageUrl": "https://cdn.onlineradiobox.com/img/l/7/7147.v16.png",
    "genre": "genre_retro",
    "country": "country_ireland"
  },
  {
    "id": "ie109",
    "name": "The Zone 102.5 FM",
    "streamUrl": "http://uk1.internet-radio.com:8355/stream",
    "imageUrl": "https://cdn.onlineradiobox.com/img/l/2/119632.v3.png",
    "genre": "genre_pop",
    "country": "country_ireland"
  },
  {
    "id": "ie110",
    "name": "Heartbeat FM",
    "streamUrl": "http://cast5.magicstreams.gr:8010/stream",
    "imageUrl": "https://cdn.onlineradiobox.com/img/l/0/7360.v9.png",
    "genre": "genre_pop",
    "country": "country_ireland"
  },
  {
    "id": "ie111",
    "name": "Kfm 97.6 FM",
    "streamUrl": "http://sirius.shoutca.st:9307/stream",
    "imageUrl": "https://cdn.onlineradiobox.com/img/l/2/7132.v5.png",
    "genre": "genre_pop",
    "country": "country_ireland"
  },
  {
    "id": "ie112",
    "name": "Gem Radio New Wave",
    "streamUrl": "https://gemradionw.radioca.st/;",
    "imageUrl": "https://cdn.onlineradiobox.com/img/l/3/111903.v4.png",
    "genre": "genre_retro",
    "country": "country_ireland"
  },
  {
    "id": "ie114",
    "name": "Radio Psychobilly",
    "streamUrl": "http://radio-psychobilly.stream.laut.fm/radio-psychobilly",
    "imageUrl": "https://assets.laut.fm/ab112c237fd76ec3e2a43ad3ac46f8e9?t=_120x120",
    "genre": "genre_rock",
    "country": "country_ireland"
  },
  {
    "id": "ie115",
    "name": "Easy Radio Ireland",
    "streamUrl": "https://nl4.mystreaming.net/uber/easymix/icecast.audio",
    "imageUrl": "https://cdn.onlineradiobox.com/img/l/0/119750.v16.png",
    "genre": "genre_relax",
    "country": "country_ireland"
  },
  {
    "id": "ie116",
    "name": "PlayFM Dublin",
    "streamUrl": "https://stream.playfmdublin.com/radio192.mp3",
    "imageUrl": "https://cdn.onlineradiobox.com/img/l/3/132673.v2.png",
    "genre": "genre_pop",
    "country": "country_ireland"
  },
  {
    "id": "ie117",
    "name": "Emerald Isle Radio",
    "streamUrl": "https://a4.asurahosting.com:6600/radio.mp3",
    "imageUrl": "https://cdn.onlineradiobox.com/img/l/9/125829.v1.png",
    "genre": "genre_pop",
    "country": "country_ireland"
  },
  {
    "id": "ie118",
    "name": "Nova Chill",
    "streamUrl": "https://25443.live.streamtheworld.com/NOVA_CHILLAAC.aac?dist=onlineradiobox",
    "imageUrl": "https://cdn.onlineradiobox.com/img/l/1/155461.v3.png",
    "genre": "genre_relax",
    "country": "country_ireland"
  },
  {
    "id": "ie119",
    "name": "The 60s Network",
    "streamUrl": "http://uk1.streamingpulse.com:7020/stream",
    "imageUrl": "https://cdn.onlineradiobox.com/img/l/1/7441.v12.png",
    "genre": "genre_retro",
    "country": "country_ireland"
  },
  {
    "id": "ie120",
    "name": "Smooth Gold Hits Radio",
    "streamUrl": "https://a4.asurahosting.com:6620/radio.mp3",
    "imageUrl": "https://cdn.onlineradiobox.com/img/l/6/90346.v8.png",
    "genre": "genre_retro",
    "country": "country_ireland"
  },
  {
    "id": "ie121",
    "name": "Louth Meath FM",
    "streamUrl": "https://live.onic.ie/stream-lmfm",
    "imageUrl": "https://cdn.onlineradiobox.com/img/l/1/7661.v10.png",
    "genre": "genre_pop",
    "country": "country_ireland"
  },
  {
    "id": "ie122",
    "name": "Flirt FM 101.3",
    "streamUrl": "http://audio-edge-kef8b.ams.s.radiomast.io/89e24041-fdab-4b2d-95bd-830f5bfda900",
    "imageUrl": "https://cdn.onlineradiobox.com/img/l/7/7637.v8.png",
    "genre": "genre_pop",
    "country": "country_ireland"
  },
  {
    "id": "ie123",
    "name": "EWTN Ireland",
    "streamUrl": "https://ewtn-sgrewind.streamguys1.com/sgrewind/sky/playlist.m3u8",
    "imageUrl": "https://cdn.onlineradiobox.com/img/l/0/7270.v5.png",
    "genre": "genre_religious",
    "country": "country_ireland"
  },
  {
    "id": "ie124",
    "name": "All 80s Jukebox",
    "streamUrl": "https://all80s.radioca.st/stream",
    "imageUrl": "https://cdn.onlineradiobox.com/img/l/9/7019.v14.png",
    "genre": "genre_retro",
    "country": "country_ireland"
  },
  {
    "id": "ie125",
    "name": "Storm North East",
    "streamUrl": "https://stormnortheast.com:8443/storm",
    "imageUrl": "https://cdn.onlineradiobox.com/img/l/2/8162.v4.png",
    "genre": "genre_pop",
    "country": "country_ireland"
  },
  {
    "id": "ie126",
    "name": "West Limerick 102 FM",
    "streamUrl": "http://s29.myradiostream.com:17796/listen.mp3",
    "imageUrl": "https://www.radio.net/175/westlimerick102.png?version=c39c93f12603342bdc37371d430213213dec79cf",
    "genre": "genre_pop",
    "country": "country_ireland"
  },
  {
    "id": "ie128",
    "name": "MPB Radio 2",
    "streamUrl": "https://live.one-tv.co.uk/listen/radio2/320k.mp3",
    "imageUrl": "https://cdn.onlineradiobox.com/img/l/0/125560.v19.png",
    "genre": "genre_pop",
    "country": "country_ireland"
  },
  {
    "id": "ie129",
    "name": "MPB Radio 2 90s and 00s",
    "streamUrl": "https://radiozender.mpbnetwerken.nl/radio2-90s00s.mp3",
    "imageUrl": "https://cdn.onlineradiobox.com/img/l/9/135009.v5.png",
    "genre": "genre_90s",
    "country": "country_ireland"
  },
  {
    "id": "ie130",
    "name": "Radio Nova International",
    "streamUrl": "https://novainternational.out.airtime.pro/novainternational_a",
    "imageUrl": "https://cdn.onlineradiobox.com/img/l/2/7142.v11.png",
    "genre": "genre_rock",
    "country": "country_ireland"
  },
  {
    "id": "ie131",
    "name": "Nova 80s",
    "streamUrl": "https://29103.live.streamtheworld.com/NOVA_80SAAC.aac?dist=onlineradiobox",
    "imageUrl": "https://cdn.onlineradiobox.com/img/l/0/155460.v4.png",
    "genre": "genre_retro",
    "country": "country_ireland"
  },
  {
    "id": "ie132",
    "name": "Cork 96 FM",
    "streamUrl": "https://live.onic.ie/stream-96fm",
    "imageUrl": "https://cdn.onlineradiobox.com/img/l/4/7644.v12.png",
    "genre": "genre_pop",
    "country": "country_ireland"
  },
  {
    "id": "ie133",
    "name": "DHR Deep House Radio",
    "streamUrl": "https://streaming.shoutcast.com/dhr",
    "imageUrl": "https://cdn.onlineradiobox.com/img/l/6/7516.v8.png",
    "genre": "genre_dance",
    "country": "country_ireland"
  },
  {
    "id": "ie134",
    "name": "Solid Gold Ireland's Radio Network",
    "streamUrl": "https://a4.asurahosting.com:6640/radio.mp3",
    "imageUrl": "https://cdn.onlineradiobox.com/img/l/7/103367.v9.png",
    "genre": "genre_retro",
    "country": "country_ireland"
  },
  {
    "id": "ie135",
    "name": "Storm IRL",
    "streamUrl": "http://c22.radioboss.fm:8478/stream",
    "imageUrl": "https://cdn.onlineradiobox.com/img/l/2/127562.v7.png",
    "genre": "genre_pop",
    "country": "country_ireland"
  },
  {
    "id": "ie136",
    "name": "Energy Ratoath",
    "streamUrl": "https://cast1.torontocast.com:2025/stream",
    "imageUrl": "https://cdn.onlineradiobox.com/img/l/4/106674.v4.png",
    "genre": "genre_dance",
    "country": "country_ireland"
  },
  {
    "id": "ie137",
    "name": "Nova Classic Rock",
    "streamUrl": "https://edge2.audioxi.com/NOVA",
    "imageUrl": "https://cdn.onlineradiobox.com/img/l/9/155459.v4.png",
    "genre": "genre_clasic",
    "country": "country_ireland"
  },
  {
    "id": "ie138",
    "name": "Dublin's 98FM",
    "streamUrl": "https://stream.audioxi.com/98",
    "imageUrl": "https://cdn.onlineradiobox.com/img/l/2/7072.v10.png",
    "genre": "genre_hits",
    "country": "country_ireland"
  },
  {
    "id": "ie139",
    "name": "MixLive.ie InsomniaFM",
    "streamUrl": "http://635.cloudrad.io:8092/stream",
    "imageUrl": "https://zeno.fm/_ipx/_/https://images.zeno.fm/lI-VtNnIhCcrf1e8cWQZaSn98J3GGFIas0C6RlJohz0/rs:fill:256:256/g:ce:0:0/aHR0cHM6Ly9wcm94eS56ZW5vLmZtL2NvbnRlbnQvc3RhdGlvbnMvOTFhNmE3MTMtYzJmOC00OWU2LTk4OWEtN2NmNzBlYzI2YzgwL2ltYWdlLz91PTE3MDE2OTY5NDIwMDA.webp",
    "genre": "genre_dance",
    "country": "country_ireland"
  },
  {
    "id": "ie140",
    "name": "Q102",
    "streamUrl": "https://live.onic.ie/stream-q102",
    "imageUrl": "https://cdn.onlineradiobox.com/img/l/3/7083.v10.png",
    "genre": "genre_pop",
    "country": "country_ireland"
  },
  {
    "id": "ie141",
    "name": "Limerick's Live 95FM",
    "streamUrl": "https://live.onic.ie/stream-live95",
    "imageUrl": "https://cdn.onlineradiobox.com/img/l/1/7701.v9.png",
    "genre": "genre_pop",
    "country": "country_ireland"
  },
  {
    "id": "ie142",
    "name": "GEM New Wave Radio",
    "streamUrl": "http://95.217.34.48:8928/stream",
    "imageUrl": "https://cdn.onlineradiobox.com/img/l/3/111903.v4.png",
    "genre": "genre_retro",
    "country": "country_ireland"
  },
  {
    "id": "ie144",
    "name": "Dublin's Q102 80s",
    "streamUrl": "https://live.onic.ie/stream-80s",
    "imageUrl": "https://cdn.onlineradiobox.com/img/l/6/117796.v3.png",
    "genre": "genre_retro",
    "country": "country_ireland"
  },
  {
    "id": "ie145",
    "name": "Symphony Radio",
    "streamUrl": "https://christmasfm.cdnstream1.com/2551_128.mp3",
    "imageUrl": "https://cdn.onlineradiobox.com/img/l/2/31602.v2.png",
    "genre": "genre_clasic",
    "country": "country_ireland"
  },
  {
    "id": "ie146",
    "name": "FM104 HitMix",
    "streamUrl": "https://live.onic.ie/stream-hits",
    "imageUrl": "https://cdn.onlineradiobox.com/img/l/5/84515.v2.png",
    "genre": "genre_hits",
    "country": "country_ireland"
  },
  {
    "id": "ie147",
    "name": "East Coast FM",
    "streamUrl": "https://live-bauerie.sharp-stream.com/EASTCOAST",
    "imageUrl": "https://cdn.onlineradiobox.com/img/l/7/7107.v4.png",
    "genre": "genre_pop",
    "country": "country_ireland"
  },
  {
    "id": "ie148",
    "name": "Connemara FM",
    "streamUrl": "https://audio-edge-ey5nr.ams.s.radiomast.io/5008371a-b8fd-4745-a5a3-e17837dad90c",
    "imageUrl": "https://cdn.onlineradiobox.com/img/l/9/7509.v9.png",
    "genre": "genre_pop",
    "country": "country_ireland"
  },
  {
    "id": "ie149",
    "name": "PowerFM Dublin",
    "streamUrl": "https://www.powerfm.org:8443/powerfm.mp3",
    "imageUrl": "https://cdn.onlineradiobox.com/img/l/3/132673.v2.png",
    "genre": "genre_pop",
    "country": "country_ireland"
  },
  {
    "id": "ie150",
    "name": "C103",
    "streamUrl": "https://live.onic.ie/stream-c103-north",
    "imageUrl": "https://cdn.onlineradiobox.com/img/l/7/7647.v9.png",
    "genre": "genre_pop",
    "country": "country_ireland"
  },
  {
    "id": "ie151",
    "name": "Solid Gold Radio Ireland 3 v2",
    "streamUrl": "https://a4.asurahosting.com:6660/radio.mp3",
    "imageUrl": "https://cdn.onlineradiobox.com/img/l/1/87021.v11.png",
    "genre": "genre_retro",
    "country": "country_ireland"
  },
  {
    "id": "is1",
    "name": "Gull Bylgjan",
    "streamUrl": "https://icecast.visir.is/orbGullBylgjan.aac",
    "imageUrl": "__________________________",
    "genre": "genre_retro",
    "country": "country_iceland"
  },
  {
    "id": "is2",
    "name": "Létt Bylgjan",
    "streamUrl": "https://icecast.visir.is/orbLettBylgjan.aac",
    "imageUrl": "__________________________",
    "genre": "genre_relax",
    "country": "country_iceland"
  },
  {
    "id": "is3",
    "name": "80s BYLGJAN",
    "streamUrl": "https://icecast.visir.is/orb80s.aac",
    "imageUrl": "__________________________",
    "genre": "genre_retro",
    "country": "country_iceland"
  },
  {
    "id": "is4",
    "name": "Suðurland FM",
    "streamUrl": "http://178.19.58.119:1818/",
    "imageUrl": "__________________________",
    "genre": "genre_pop",
    "country": "country_iceland"
  },
  {
    "id": "is5",
    "name": "Trölli",
    "streamUrl": "http://live.trolli.is:8200/",
    "imageUrl": "__________________________",
    "genre": "genre_pop",
    "country": "country_iceland"
  },
  {
    "id": "is6",
    "name": "Íslenska Bylgjan",
    "streamUrl": "https://live.visir.is/hls-radio/fmx/playlist.m3u8",
    "imageUrl": "__________________________",
    "genre": "genre_pop",
    "country": "country_iceland"
  },
  {
    "id": "is7",
    "name": "Snow Radio Network",
    "streamUrl": "https://15113.live.streamtheworld.com/SAM02AAC45_SC?pname=TDSdk",
    "imageUrl": "__________________________",
    "genre": "genre_pop",
    "country": "country_iceland"
  },
  {
    "id": "is8",
    "name": "Apparat id",
    "streamUrl": "http://icecast.365net.is:8000/orbApparatid.aac",
    "imageUrl": "__________________________",
    "genre": "genre_pop",
    "country": "country_iceland"
  },
  {
    "id": "is9",
    "name": "X-id 97.7 FM",
    "streamUrl": "https://icecast.visir.is/orbXid.aac",
    "imageUrl": "__________________________",
    "genre": "genre_pop",
    "country": "country_iceland"
  },
  {
    "id": "is10",
    "name": "Ice FM",
    "streamUrl": "http://falcon.shoutca.st:8516",
    "imageUrl": "__________________________",
    "genre": "genre_pop",
    "country": "country_iceland"
  },
  {
    "id": "is11",
    "name": "FM 957 Extra",
    "streamUrl": "https://live.visir.is/hls-radio/fmextra/playlist.m3u8",
    "imageUrl": "__________________________",
    "genre": "genre_pop",
    "country": "country_iceland"
  },
  {
    "id": "is12",
    "name": "Bylgjan FM",
    "streamUrl": "https://live.visir.is/hls-radio/bylgjan/playlist.m3u8",
    "imageUrl": "__________________________",
    "genre": "genre_pop",
    "country": "country_iceland"
  },
  {
    "id": "is13",
    "name": "FM 957",
    "streamUrl": "https://icecast.visir.is/orbFm957.aac",
    "imageUrl": "__________________________",
    "genre": "genre_pop",
    "country": "country_iceland"
  },
  {
    "id": "is14",
    "name": "Rondo",
    "streamUrl": "https://ruv-radio-live.akamaized.net/streymi/rondo/rondo-256000.m3u8",
    "imageUrl": "__________________________",
    "genre": "genre_clasic",
    "country": "country_iceland"
  },
  {
    "id": "is15",
    "name": "Bikini FM Marina Alta - Sur",
    "streamUrl": "https://stream.mediasector.es/radio/8030/bikinifm-marina-alta-sur.mp3",
    "imageUrl": "__________________________",
    "genre": "genre_pop",
    "country": "country_iceland"
  },
  {
    "id": "is16",
    "name": "Jovem Pan - JP News Joinville",
    "streamUrl": "https://ssl1.transmissaodigital.com:2398/server",
    "imageUrl": "__________________________",
    "genre": "genre_news",
    "country": "country_iceland"
  },
  {
    "id": "is17",
    "name": "Street Deejays",
    "streamUrl": "https://stream.zeno.fm/nbwdnxz7na0uv.aac",
    "imageUrl": "__________________________",
    "genre": "genre_dance",
    "country": "country_iceland"
  },
  {
    "id": "is18",
    "name": "Dance Family",
    "streamUrl": "https://stream.laut.fm/dance-family-radio",
    "imageUrl": "__________________________",
    "genre": "genre_dance",
    "country": "country_iceland"
  },
  {
    "id": "is19",
    "name": "House Music Channel - Loops",
    "streamUrl": "https://ssl190.ozelip.com/asistan/stream/ebcc933e674242c816bd38923148d46e",
    "imageUrl": "__________________________",
    "genre": "genre_dance",
    "country": "country_iceland"
  },
  {
    "id": "is20",
    "name": "Bylgjan 989",
    "streamUrl": "http://icecast.365net.is:8000/orbbylgjan.aac",
    "imageUrl": "__________________________",
    "genre": "genre_pop",
    "country": "country_iceland"
  },
  {
    "id": "is21",
    "name": "FlashBack 60s",
    "streamUrl": "http://stream3.radio.is:443/60flashback",
    "imageUrl": "__________________________",
    "genre": "genre_retro",
    "country": "country_iceland"
  },
  {
    "id": "is22",
    "name": "FlashBack 70s",
    "streamUrl": "http://ice-11.spilarinn.is/70flashback",
    "imageUrl": "__________________________",
    "genre": "genre_retro",
    "country": "country_iceland"
  },
  {
    "id": "is23",
    "name": "FlashBack 80s",
    "streamUrl": "http://stream3.radio.is:443/80flashback",
    "imageUrl": "__________________________",
    "genre": "genre_retro",
    "country": "country_iceland"
  },
  {
    "id": "is24",
    "name": "FlashBack 90s",
    "streamUrl": "http://stream3.radio.is:443/90flashback",
    "imageUrl": "__________________________",
    "genre": "genre_retro",
    "country": "country_iceland"
  },
  {
    "id": "is25",
    "name": "FlashBack 91.9 FM",
    "streamUrl": "http://stream3.radio.is:443/flashback",
    "imageUrl": "__________________________",
    "genre": "genre_retro",
    "country": "country_iceland"
  },
  {
    "id": "is26",
    "name": "FM Extra",
    "streamUrl": "http://icecast.365net.is:8000/orbFmExtra.aac",
    "imageUrl": "__________________________",
    "genre": "genre_pop",
    "country": "country_iceland"
  },
  {
    "id": "is27",
    "name": "FM Xtra 101.5 FM",
    "streamUrl": "http://radio.is:443/fmxtra",
    "imageUrl": "__________________________",
    "genre": "genre_pop",
    "country": "country_iceland"
  },
  {
    "id": "is28",
    "name": "FMX Klassik",
    "streamUrl": "http://icecast.365net.is:8000/orbFMX.aac",
    "imageUrl": "__________________________",
    "genre": "genre_clasic",
    "country": "country_iceland"
  },
  {
    "id": "is29",
    "name": "Gull Bylgjan 909",
    "streamUrl": "http://icecast.365net.is:8000/orbGullBylgjan.aac",
    "imageUrl": "__________________________",
    "genre": "genre_retro",
    "country": "country_iceland"
  },
  {
    "id": "is30",
    "name": "Kaninn FM 100.5",
    "streamUrl": "http://radio.is:443/kaninnmobile",
    "imageUrl": "__________________________",
    "genre": "genre_pop",
    "country": "country_iceland"
  },
  {
    "id": "is31",
    "name": "KissFM 104.5",
    "streamUrl": "http://stream3.radio.is:443/kissfm",
    "imageUrl": "__________________________",
    "genre": "genre_pop",
    "country": "country_iceland"
  },
  {
    "id": "is32",
    "name": "Lindin 102.9 FM",
    "streamUrl": "http://62.145.147.50:8001/lindin",
    "imageUrl": "__________________________",
    "genre": "genre_religious",
    "country": "country_iceland"
  },
  {
    "id": "is33",
    "name": "Rás 1 RÚV 93.5 FM",
    "streamUrl": "http://netradio.ruv.is:80/ras1.mp3",
    "imageUrl": "__________________________",
    "genre": "genre_news",
    "country": "country_iceland"
  },
  {
    "id": "is34",
    "name": "Rás 2 RÚV 90.1 FM",
    "streamUrl": "http://netradio.ruv.is:80/ras2.mp3",
    "imageUrl": "__________________________",
    "genre": "genre_news",
    "country": "country_iceland"
  },
  {
    "id": "is35",
    "name": "Rondó RÚV 87.7 FM",
    "streamUrl": "http://netradio.ruv.is:80/rondo.mp3",
    "imageUrl": "__________________________",
    "genre": "genre_clasic",
    "country": "country_iceland"
  },
  {
    "id": "is36",
    "name": "RÚV Núll Pop",
    "streamUrl": "http://netradio.ruv.is:80/ruvnull.mp3",
    "imageUrl": "__________________________",
    "genre": "genre_news",
    "country": "country_iceland"
  },
  {
    "id": "is37",
    "name": "Útvarp Saga 99.4 FM",
    "streamUrl": "http://stream.utvarpsaga.is/Hljodver",
    "imageUrl": "__________________________",
    "genre": "genre_news",
    "country": "country_iceland"
  },
  {
    "id": "is38",
    "name": "X 97.7",
    "streamUrl": "http://icecast.365net.is:8000/orbXid.aac",
    "imageUrl": "__________________________",
    "genre": "genre_pop",
    "country": "country_iceland"
  },
  {
    "id": "is39",
    "name": "Flashback 80s 101.5",
    "streamUrl": "https://ice-11.spilarinn.is/80flashback",
    "imageUrl": "__________________________",
    "genre": "genre_retro",
    "country": "country_iceland"
  },
  {
    "id": "is40",
    "name": "Sudurland FM",
    "streamUrl": "https://ice-11.spilarinn.is/tsudurlandfm",
    "imageUrl": "__________________________",
    "genre": "genre_pop",
    "country": "country_iceland"
  },
  {
    "id": "is41",
    "name": "Utvarp Saga FM",
    "streamUrl": "https://ice-11.spilarinn.is/saga",
    "imageUrl": "__________________________",
    "genre": "genre_news",
    "country": "country_iceland"
  },
  {
    "id": "is42",
    "name": "RÚV - Rás 1",
    "streamUrl": "http://netradio.ruv.is/ras1.mp3",
    "imageUrl": "__________________________",
    "genre": "genre_news",
    "country": "country_iceland"
  },
  {
    "id": "is43",
    "name": "Utvarp Saga",
    "streamUrl": "http://stream.utvarpsaga.is:80/Hljodver",
    "imageUrl": "__________________________",
    "genre": "genre_news",
    "country": "country_iceland"
  },
  {
    "id": "is44",
    "name": "K100",
    "streamUrl": "https://k100straumar.mbl.is/kaninnmobile",
    "imageUrl": "__________________________",
    "genre": "genre_pop",
    "country": "country_iceland"
  },
  {
    "id": "is45",
    "name": "3ABN",
    "streamUrl": "http://war.str3am.com:7180/live",
    "imageUrl": "__________________________",
    "genre": "genre_religious",
    "country": "country_iceland"
  },
  {
    "id": "is46",
    "name": "KissFM Iceland",
    "streamUrl": "http://ice-11.spilarinn.is/kissfm",
    "imageUrl": "__________________________",
    "genre": "genre_pop",
    "country": "country_iceland"
  },
  {
    "id": "is47",
    "name": "RÚV - Rás 2",
    "streamUrl": "http://netradio.ruv.is/ras2.mp3",
    "imageUrl": "__________________________",
    "genre": "genre_news",
    "country": "country_iceland"
  },
  {
    "id": "is48",
    "name": "Utvarp Bodun",
    "streamUrl": "http://bodun.is:8000/stream",
    "imageUrl": "__________________________",
    "genre": "genre_religious",
    "country": "country_iceland"
  },
  {
    "id": "is49",
    "name": "FlashBack",
    "streamUrl": "http://stream.radio.is:443/flashback",
    "imageUrl": "__________________________",
    "genre": "genre_retro",
    "country": "country_iceland"
  },
  {
    "id": "is50",
    "name": "Retro 895",
    "streamUrl": "http://radio.is:443/retromobile",
    "imageUrl": "__________________________",
    "genre": "genre_retro",
    "country": "country_iceland"
  },
  {
    "id": "is51",
    "name": "FM Xtra",
    "streamUrl": "http://www.radio.is:443/fmxtra",
    "imageUrl": "__________________________",
    "genre": "genre_pop",
    "country": "country_iceland"
  },
  {
    "id": "is52",
    "name": "5",
    "streamUrl": "http://www.radio.is:443/kiss",
    "imageUrl": "__________________________",
    "genre": "genre_pop",
    "country": "country_iceland"
  },
  {
    "id": "is53",
    "name": "Apparatid",
    "streamUrl": "https://live.visir.is/hls-radio/apparatid/playlist.m3u8",
    "imageUrl": "__________________________",
    "genre": "genre_pop",
    "country": "country_iceland"
  },
  {
    "id": "is54",
    "name": "Bitter Sweet Music IS",
    "streamUrl": "http://91.121.236.34:8520/is",
    "imageUrl": "__________________________",
    "genre": "genre_retro",
    "country": "country_iceland"
  },
  {
    "id": "is55",
    "name": "FlashBack FM",
    "streamUrl": "https://ice-11.spilarinn.is/flashback",
    "imageUrl": "__________________________",
    "genre": "genre_retro",
    "country": "country_iceland"
  },
  {
    "id": "is56",
    "name": "FM957",
    "streamUrl": "https://live.visir.is/hls-radio/fm957/playlist.m3u8",
    "imageUrl": "__________________________",
    "genre": "genre_pop",
    "country": "country_iceland"
  },
  {
    "id": "is57",
    "name": "Lindin",
    "streamUrl": "http://62.145.147.50:8001/stream.aac",
    "imageUrl": "__________________________",
    "genre": "genre_religious",
    "country": "country_iceland"
  },
  {
    "id": "is58",
    "name": "RÚV  Rás 1",
    "streamUrl": "https://ruv-radio-live.akamaized.net/streymi/ras1/ras1.m3u8",
    "imageUrl": "__________________________",
    "genre": "genre_news",
    "country": "country_iceland"
  },
  {
    "id": "is59",
    "name": "RÚV Rás 2",
    "streamUrl": "https://ruv-ras2-live-hls.secure.footprint.net/hls-live/ruv-ras2/_definst_/live.m3u8",
    "imageUrl": "__________________________",
    "genre": "genre_news",
    "country": "country_iceland"
  },
  {
    "id": "is60",
    "name": "RÚV Rondó",
    "streamUrl": "https://ruv-rondo-live-hls.secure.footprint.net/hls-live/ruv-ras3/_definst_/live.m3u8",
    "imageUrl": "__________________________",
    "genre": "genre_clasic",
    "country": "country_iceland"
  },
  {
    "id": "is61",
    "name": "Útvarp Reykjavíkur í beinni",
    "streamUrl": "https://stream2.svrdedicado.org:7127/stream",
    "imageUrl": "__________________________",
    "genre": "genre_pop",
    "country": "country_iceland"
  },
  {
    "id": "is62",
    "name": "Krúttin",
    "streamUrl": "http://radio.kruttin.com/stream/turteldufur/",
    "imageUrl": "__________________________",
    "genre": "genre_kids",
    "country": "country_iceland"
  },
  {
    "id": "is63",
    "name": "DJ Danni - Hands Up",
    "streamUrl": "http://server.skagarasin.com:8300/",
    "imageUrl": "__________________________",
    "genre": "genre_dance",
    "country": "country_iceland"
  },
  {
    "id": "is64",
    "name": "Jólarásin / Christmas",
    "streamUrl": "http://s35.myradiostream.com:6396/",
    "imageUrl": "__________________________",
    "genre": "genre_pop",
    "country": "country_iceland"
  },
  {
    "id": "is65",
    "name": "Hringbraut",
    "streamUrl": "http://www.radio.is:443/hrb",
    "imageUrl": "__________________________",
    "genre": "genre_pop",
    "country": "country_iceland"
  },
  {
    "id": "is66",
    "name": "Zoom 25",
    "streamUrl": "http://51.254.216.57:8090/zoom25_live",
    "imageUrl": "__________________________",
    "genre": "genre_dance",
    "country": "country_iceland"
  },
  {
    "id": "is67",
    "name": "Rispan",
    "streamUrl": "http://212.30.222.59:2424/",
    "imageUrl": "__________________________",
    "genre": "genre_pop",
    "country": "country_iceland"
  },
  {
    "id": "is68",
    "name": "7",
    "streamUrl": "http://listen.shoutcast.com/UtvarpAkureyriFM98-7",
    "imageUrl": "__________________________",
    "genre": "genre_pop",
    "country": "country_iceland"
  },
  {
    "id": "is69",
    "name": "Rúv rás1",
    "streamUrl": "http://netradio.ruv.is/ras1.aac",
    "imageUrl": "__________________________",
    "genre": "genre_news",
    "country": "country_iceland"
  },
  {
    "id": "is70",
    "name": "80's Bylgjan",
    "streamUrl": "http://icecast.365net.is:8000/orb80s.aac",
    "imageUrl": "__________________________",
    "genre": "genre_retro",
    "country": "country_iceland"
  },
  {
    "id": "is71",
    "name": "Rás2",
    "streamUrl": "http://netradio.ruv.is/ras2.aac",
    "imageUrl": "__________________________",
    "genre": "genre_pop",
    "country": "country_iceland"
  },
  {
    "id": "is72",
    "name": "80´s Flash Back",
    "streamUrl": "http://ice-11.spilarinn.is/80flashback",
    "imageUrl": "__________________________",
    "genre": "genre_retro",
    "country": "country_iceland"
  },
  {
    "id": "is73",
    "name": "Visir \"FM957\" 95.7 Reykjavik",
    "streamUrl": "http://icecast.365net.is:8000/orbFm957.aac",
    "imageUrl": "__________________________",
    "genre": "genre_pop",
    "country": "country_iceland"
  },
  {
    "id": "is74",
    "name": "Radio Bodun 105.5 Reykjavik",
    "streamUrl": "http://radio.bodun.is:8000/stream",
    "imageUrl": "__________________________",
    "genre": "genre_religious",
    "country": "country_iceland"
  },
  {
    "id": "is75",
    "name": "Útvarp Saga",
    "streamUrl": "https://stream.utvarpsaga.is/Hljodver",
    "imageUrl": "__________________________",
    "genre": "genre_news",
    "country": "country_iceland"
  },
  {
    "id": "is76",
    "name": "Rondó",
    "streamUrl": "https://ruv-radio-live.akamaized.net/streymi/rondo/rondo.m3u8",
    "imageUrl": "__________________________",
    "genre": "genre_clasic",
    "country": "country_iceland"
  },
  {
    "id": "is77",
    "name": "Cathedral 13",
    "streamUrl": "http://listen.shoutcast.com/cathedralxiii",
    "imageUrl": "__________________________",
    "genre": "genre_religious",
    "country": "country_iceland"
  },
  {
    "id": "is78",
    "name": "K 100",
    "streamUrl": "https://ice-11.spilarinn.is/kaninnmobile",
    "imageUrl": "__________________________",
    "genre": "genre_pop",
    "country": "country_iceland"
  },
  {
    "id": "is79",
    "name": "Fred Film Radio-26 Íslenska",
    "streamUrl": "https://s10.webradio-hosting.com/proxy/fredradiois/stream",
    "imageUrl": "__________________________",
    "genre": "genre_pop",
    "country": "country_iceland"
  },
  {
    "id": "is80",
    "name": "Abdulbasit Abdulsamad",
    "streamUrl": "https://radio.mp3islam.com/listen/abdulbasit/radio.mp3",
    "imageUrl": "__________________________",
    "genre": "genre_religious",
    "country": "country_iceland"
  },
  {
    "id": "is81",
    "name": "Cork's 96fm",
    "streamUrl": "http://wg.cdn.tibus.net/96fm",
    "imageUrl": "__________________________",
    "genre": "genre_pop",
    "country": "country_iceland"
  },
  {
    "id": "is82",
    "name": "C103 North",
    "streamUrl": "http://wg.cdn.tibus.net/C103",
    "imageUrl": "__________________________",
    "genre": "genre_pop",
    "country": "country_iceland"
  },
  {
    "id": "is83",
    "name": "FRED FILM RADIO CH26 Icelandic",
    "streamUrl": "http://91.121.139.194:8110/stream",
    "imageUrl": "__________________________",
    "genre": "genre_pop",
    "country": "country_iceland"
  },
  {
    "id": "is84",
    "name": "FMX",
    "streamUrl": "https://fmradiohub.in/radio?url=http://icecast.365net.is:8000/orbFMX.aac",
    "imageUrl": "__________________________",
    "genre": "genre_pop",
    "country": "country_iceland"
  },
  {
    "id": "is85",
    "name": "RÚV Rás 1",
    "streamUrl": "https://prod-54-224-126-57.wostreaming.net/saga-wxstfmmp3-ibc1?",
    "imageUrl": "__________________________",
    "genre": "genre_news",
    "country": "country_iceland"
  },
  {
    "id": "is86",
    "name": "Apparatið",
    "streamUrl": "https://live.visir.is/hls-radio/apparatid/chunklist_DVR.m3u8",
    "imageUrl": "__________________________",
    "genre": "genre_pop",
    "country": "country_iceland"
  },
  {
    "id": "is87",
    "name": "FMX Klassík",
    "streamUrl": "https://live.visir.is/hls-radio/fmx/chunklist_DVR.m3u8",
    "imageUrl": "__________________________",
    "genre": "genre_pop",
    "country": "country_iceland"
  },
  {
    "id": "is88",
    "name": "Rás 1",
    "streamUrl": "https://ruv-ras1-live-hls.secure.footprint.net/hls-live/ruv-ras1/_definst_/live.m3u8",
    "imageUrl": "__________________________",
    "genre": "genre_news",
    "country": "country_iceland"
  },
  {
    "id": "is89",
    "name": "Flashback 60's Online - Reykjavik",
    "streamUrl": "http://radio.is:443/60flashback",
    "imageUrl": "__________________________",
    "genre": "genre_retro",
    "country": "country_iceland"
  },
  {
    "id": "is90",
    "name": "Flashback 80's 101.5 Reykjavik",
    "streamUrl": "http://www.radio.is:443/80flashback",
    "imageUrl": "__________________________",
    "genre": "genre_retro",
    "country": "country_iceland"
  },
  {
    "id": "is91",
    "name": "Flashback 90's Online Reykjavik",
    "streamUrl": "http://www.radio.is:443/90flashback",
    "imageUrl": "__________________________",
    "genre": "genre_retro",
    "country": "country_iceland"
  },
  {
    "id": "is92",
    "name": "Flashback 91.9 Reykjavik",
    "streamUrl": "http://www.radio.is:443/flashback",
    "imageUrl": "__________________________",
    "genre": "genre_retro",
    "country": "country_iceland"
  },
  {
    "id": "is93",
    "name": "FMX Klassik 103.9 Reykjavik",
    "streamUrl": "http://vcache1.365net.is/hls-radio/fmx/master.m3u8",
    "imageUrl": "__________________________",
    "genre": "genre_clasic",
    "country": "country_iceland"
  },
  {
    "id": "is94",
    "name": "Gull Bylgjan 90.9 Reykjavik",
    "streamUrl": "http://icecast.365net.is:8000/orbGullBylgjan.aac.m3u",
    "imageUrl": "__________________________",
    "genre": "genre_retro",
    "country": "country_iceland"
  },
  {
    "id": "is95",
    "name": "Kannin FM 100.5 \"K100\" Reykjavik",
    "streamUrl": "http://www.radio.is:443/kaninnmobile",
    "imageUrl": "__________________________",
    "genre": "genre_pop",
    "country": "country_iceland"
  },
  {
    "id": "is96",
    "name": "Kiss FM 104.5 Reykjavik",
    "streamUrl": "http://stream.radio.is:443/kiss",
    "imageUrl": "__________________________",
    "genre": "genre_pop",
    "country": "country_iceland"
  },
  {
    "id": "is97",
    "name": "Retro FM 89.5",
    "streamUrl": "http://www.radio.is:443/retromobile",
    "imageUrl": "__________________________",
    "genre": "genre_retro",
    "country": "country_iceland"
  },
  {
    "id": "is98",
    "name": "Saga 99.4 Reykjavik",
    "streamUrl": "http://www.radio.is:443/saga",
    "imageUrl": "__________________________",
    "genre": "genre_news",
    "country": "country_iceland"
  },
  {
    "id": "is99",
    "name": "X977",
    "streamUrl": "http://icecast.365net.is:8000/orbXid.aac.m3u",
    "imageUrl": "__________________________",
    "genre": "genre_pop",
    "country": "country_iceland"
  },
  {
    "id": "is100",
    "name": "Prufa",
    "streamUrl": "https://198.245.61.103:8119/index.html",
    "imageUrl": "__________________________",
    "genre": "genre_pop",
    "country": "country_iceland"
  },
  {
    "id": "is101",
    "name": "Italian Best Music",
    "streamUrl": "http://streaming.radionomy.com/JamendoLounge",
    "imageUrl": "__________________________",
    "genre": "genre_pop",
    "country": "country_iceland"
  },
  {
    "id": "is102",
    "name": "Lett Bylgjan",
    "streamUrl": "http://icecast.365net.is:8000/orbLettBylgjan.aac",
    "imageUrl": "__________________________",
    "genre": "genre_relax",
    "country": "country_iceland"
  },
  {
    "id": "is103",
    "name": "ICE FM Iceland",
    "streamUrl": "http://37.59.28.208:8188/",
    "imageUrl": "__________________________",
    "genre": "genre_pop",
    "country": "country_iceland"
  },
  {
    "id": "is104",
    "name": "RV Nll",
    "streamUrl": "http://netradio.ruv.is:80/ruvnull.aac",
    "imageUrl": "__________________________",
    "genre": "genre_pop",
    "country": "country_iceland"
  },
  {
    "id": "is105",
    "name": "RV Rond",
    "streamUrl": "http://netradio.ruv.is:80/rondo.aac",
    "imageUrl": "__________________________",
    "genre": "genre_pop",
    "country": "country_iceland"
  },
  {
    "id": "is106",
    "name": "Kiss FM",
    "streamUrl": "https://ice-11.spilarinn.is/kiss",
    "imageUrl": "__________________________",
    "genre": "genre_pop",
    "country": "country_iceland"
  },
  {
    "id": "is107",
    "name": "Retro 89.5",
    "streamUrl": "https://ice-11.spilarinn.is/retromobile",
    "imageUrl": "__________________________",
    "genre": "genre_retro",
    "country": "country_iceland"
  },
  {
    "id": "is108",
    "name": "Útvarp 101",
    "streamUrl": "https://stream.101.live/audio/101/chunklist.m3u8",
    "imageUrl": "__________________________",
    "genre": "genre_pop",
    "country": "country_iceland"
  },
  {
    "id": "is109",
    "name": "96 FM",
    "streamUrl": "https://corus.leanstream.co/CFPLFM",
    "imageUrl": "__________________________",
    "genre": "genre_pop",
    "country": "country_iceland"
  },
  {
    "id": "is110",
    "name": "98 FM",
    "streamUrl": "https://stream.audioxi.com/98",
    "imageUrl": "__________________________",
    "genre": "genre_pop",
    "country": "country_iceland"
  },
  {
    "id": "is111",
    "name": "001Manimaa hd",
    "streamUrl": "https://stream.zeno.fm/n655rxm0238uv",
    "imageUrl": "__________________________",
    "genre": "genre_pop",
    "country": "country_iceland"
  },
  {
    "id": "is112",
    "name": "JamRock",
    "streamUrl": "https://stream.zeno.fm/rcmergybtpmtv",
    "imageUrl": "__________________________",
    "genre": "genre_rock",
    "country": "country_iceland"
  },
  {
    "id": "is113",
    "name": "Radio Perro Artico",
    "streamUrl": "https://stream.zeno.fm/p9bpmbketc9uv",
    "imageUrl": "__________________________",
    "genre": "genre_pop",
    "country": "country_iceland"
  },
  {
    "id": "is114",
    "name": "The Howling Tomb",
    "streamUrl": "https://stream.zeno.fm/hyw46x53z98uv",
    "imageUrl": "__________________________",
    "genre": "genre_pop",
    "country": "country_iceland"
  },
  {
    "id": "is115",
    "name": "Gingery",
    "streamUrl": "https://stream.zeno.fm/im5uhpiwz9dvv",
    "imageUrl": "__________________________",
    "genre": "genre_pop",
    "country": "country_iceland"
  },
  {
    "id": "is116",
    "name": "Boudoir",
    "streamUrl": "https://stream.zeno.fm/8fk3s6yegphvv",
    "imageUrl": "__________________________",
    "genre": "genre_pop",
    "country": "country_iceland"
  },
  {
    "id": "is117",
    "name": "Útvarp Keflavík",
    "streamUrl": "https://stream.zeno.fm/hhdck8pvbphvv",
    "imageUrl": "__________________________",
    "genre": "genre_pop",
    "country": "country_iceland"
  },
  {
    "id": "is118",
    "name": "Anuel AA",
    "streamUrl": "https://stream.zeno.fm/485qy7ewwchvv",
    "imageUrl": "__________________________",
    "genre": "genre_pop",
    "country": "country_iceland"
  },
  {
    "id": "is119",
    "name": "Radio Perro",
    "streamUrl": "https://stream.zeno.fm/b78ugghetc9uv",
    "imageUrl": "__________________________",
    "genre": "genre_pop",
    "country": "country_iceland"
  },
  {
    "id": "is120",
    "name": "Jax ling official radio station",
    "streamUrl": "https://stream.zeno.fm/qay2essawuhvv",
    "imageUrl": "__________________________",
    "genre": "genre_pop",
    "country": "country_iceland"
  },
  {
    "id": "is121",
    "name": "prufan",
    "streamUrl": "https://stream.zeno.fm/dw8p60d4xuhvv",
    "imageUrl": "__________________________",
    "genre": "genre_pop",
    "country": "country_iceland"
  },
  {
    "id": "is122",
    "name": "Diseased",
    "streamUrl": "https://stream.zeno.fm/t5re44ttta0uv",
    "imageUrl": "__________________________",
    "genre": "genre_pop",
    "country": "country_iceland"
  },
  {
    "id": "is123",
    "name": "Radio Frytki 24H LIVE ON (ONLY MUSIC)",
    "streamUrl": "https://stream.zeno.fm/4jbp2tq7jvqtv",
    "imageUrl": "__________________________",
    "genre": "genre_pop",
    "country": "country_iceland"
  },
  {
    "id": "is124",
    "name": "utvarpið",
    "streamUrl": "https://stream.zeno.fm/5c3u29xwp68uv",
    "imageUrl": "__________________________",
    "genre": "genre_pop",
    "country": "country_iceland"
  },
  {
    "id": "is125",
    "name": "Dannys Rock Station",
    "streamUrl": "https://stream.zeno.fm/6e3asd896nhvv",
    "imageUrl": "__________________________",
    "genre": "genre_rock",
    "country": "country_iceland"
  },
  {
    "id": "is126",
    "name": "The First Time",
    "streamUrl": "https://stream.zeno.fm/1duy32n43hhvv",
    "imageUrl": "__________________________",
    "genre": "genre_pop",
    "country": "country_iceland"
  },
  {
    "id": "is127",
    "name": "radio c",
    "streamUrl": "https://stream.zeno.fm/u9xzva5hpd0uv",
    "imageUrl": "__________________________",
    "genre": "genre_pop",
    "country": "country_iceland"
  },
  {
    "id": "is128",
    "name": "Poland from Hetalia Marukaite Chikyuu FM",
    "streamUrl": "https://stream.zeno.fm/qe3nk3gp2zhvv",
    "imageUrl": "__________________________",
    "genre": "genre_pop",
    "country": "country_iceland"
  },
  {
    "id": "is129",
    "name": "Tzgospel (Iceland)",
    "streamUrl": "https://stream.zeno.fm/dc122f8u2ehvv",
    "imageUrl": "__________________________",
    "genre": "genre_religious",
    "country": "country_iceland"
  },
  {
    "id": "is130",
    "name": "Unholy",
    "streamUrl": "https://stream.zeno.fm/41y996trua0uv",
    "imageUrl": "__________________________",
    "genre": "genre_pop",
    "country": "country_iceland"
  },
  {
    "id": "is131",
    "name": "1vijikandh",
    "streamUrl": "https://stream.zeno.fm/v5t0ysd9938uv",
    "imageUrl": "__________________________",
    "genre": "genre_pop",
    "country": "country_iceland"
  },
  {
    "id": "is132",
    "name": "LOAT",
    "streamUrl": "https://stream.zeno.fm/e6a1gpmxznhvv",
    "imageUrl": "__________________________",
    "genre": "genre_pop",
    "country": "country_iceland"
  },
  {
    "id": "is133",
    "name": "Radio Frytki 24h LIVE ON",
    "streamUrl": "https://stream.zeno.fm/93xzfhatmwxtv",
    "imageUrl": "__________________________",
    "genre": "genre_pop",
    "country": "country_iceland"
  },
  {
    "id": "is134",
    "name": "Skaga Rásin",
    "streamUrl": "https://stream.zeno.fm/0b1q040fuuhvv",
    "imageUrl": "__________________________",
    "genre": "genre_dance",
    "country": "country_iceland"
  },
  {
    "id": "is135",
    "name": "The tech community",
    "streamUrl": "https://stream.zeno.fm/b3xpzbdfeq8uv",
    "imageUrl": "__________________________",
    "genre": "genre_pop",
    "country": "country_iceland"
  },
  {
    "id": "is136",
    "name": "asdsdad",
    "streamUrl": "https://stream.zeno.fm/zzfjff5jch0vv",
    "imageUrl": "__________________________",
    "genre": "genre_pop",
    "country": "country_iceland"
  },
  {
    "id": "is137",
    "name": "Effaþa",
    "streamUrl": "https://stream.zeno.fm/aa61r7cdfc9uv",
    "imageUrl": "__________________________",
    "genre": "genre_pop",
    "country": "country_iceland"
  },
  {
    "id": "is138",
    "name": "ABBYY FineReader 11 64",
    "streamUrl": "https://stream.zeno.fm/odxzhzufoimuv",
    "imageUrl": "__________________________",
    "genre": "genre_pop",
    "country": "country_iceland"
  },
  {
    "id": "is139",
    "name": "ÁttanFM",
    "streamUrl": "http://www.radio.is:443/attan",
    "imageUrl": "__________________________",
    "genre": "genre_pop",
    "country": "country_iceland"
  },
  {
    "id": "is140",
    "name": "Ice FM Online",
    "streamUrl": "http://37.59.28.208:8188/stream/",
    "imageUrl": "__________________________",
    "genre": "genre_pop",
    "country": "country_iceland"
  },
  {
    "id": "is141",
    "name": "RÚV",
    "streamUrl": "http://sip-live.hds.adaptive.level3.net/hls-live/ruv-ras2/_definst_/live.m3u8",
    "imageUrl": "__________________________",
    "genre": "genre_news",
    "country": "country_iceland"
  },
  {
    "id": "is142",
    "name": "Sudurland FM 96.3",
    "streamUrl": "http://stream3.radio.is:443/saga",
    "imageUrl": "__________________________",
    "genre": "genre_pop",
    "country": "country_iceland"
  },
  {
    "id": "is143",
    "name": "RUV Ras 1",
    "streamUrl": "https://ruv-ras1-live-hls.secure.footprint.net/hls-live/ruv-ras1/_definst_/live/stream1.m3u8",
    "imageUrl": "__________________________",
    "genre": "genre_news",
    "country": "country_iceland"
  },
  {
    "id": "is144",
    "name": "Making Waves",
    "streamUrl": "https://stream.zeno.fm/5dgevfbqyhhvv",
    "imageUrl": "__________________________",
    "genre": "genre_pop",
    "country": "country_iceland"
  },
  {
    "id": "is145",
    "name": "Radio Deep Underground",
    "streamUrl": "http://radiodeepunderground.com:8000/rdu.mp3",
    "imageUrl": "__________________________",
    "genre": "genre_rock",
    "country": "country_iceland"
  },
  {
    "id": "is146",
    "name": "We Are The Brians",
    "streamUrl": "http://thebrians.mynetgear.com:8000/radio.mp3",
    "imageUrl": "__________________________",
    "genre": "genre_pop",
    "country": "country_iceland"
  },
  {
    "id": "is147",
    "name": "Íslenska Skaga Rásin",
    "streamUrl": "http://1985.is:8218/skagarasinis",
    "imageUrl": "__________________________",
    "genre": "genre_dance",
    "country": "country_iceland"
  },
  {
    "id": "is148",
    "name": "Útvarp Boðun",
    "streamUrl": "https://bodun.is:8443/stream?type=.mp3",
    "imageUrl": "__________________________",
    "genre": "genre_religious",
    "country": "country_iceland"
  },
  {
    "id": "is149",
    "name": "KrakkaRÚV",
    "streamUrl": "http://sip-live.hds.adaptive.level3.net/hls-live/ruv-ras4/_definst_/live.m3u8",
    "imageUrl": "__________________________",
    "genre": "genre_news",
    "country": "country_iceland"
  },
  {
    "id": "is150",
    "name": "FRED FILM RADIO Icelandic",
    "streamUrl": "http://s6.webradio-hosting.com:8110/",
    "imageUrl": "__________________________",
    "genre": "genre_pop",
    "country": "country_iceland"
  },
  {
    "id": "is151",
    "name": "KFM Iceland",
    "streamUrl": "http://s28.myradiostream.com:28330/listen.mp3",
    "imageUrl": "__________________________",
    "genre": "genre_pop",
    "country": "country_iceland"
  },
  {
    "id": "is152",
    "name": "Jóla Skaga Rásin",
    "streamUrl": "https://jol.skagarasin.is",
    "imageUrl": "__________________________",
    "genre": "genre_dance",
    "country": "country_iceland"
  },
  {
    "id": "is153",
    "name": "Flashback 60’s",
    "streamUrl": "http://ice-11.spilarinn.is/60flashback",
    "imageUrl": "__________________________",
    "genre": "genre_retro",
    "country": "country_iceland"
  },
  {
    "id": "is154",
    "name": "Retró Skaga Rásin",
    "streamUrl": "http://1985.is:8220/skagarasinretro",
    "imageUrl": "__________________________",
    "genre": "genre_retro",
    "country": "country_iceland"
  },
  {
    "id": "is155",
    "name": "Flashback 90’s",
    "streamUrl": "http://ice-11.spilarinn.is/90flashback",
    "imageUrl": "__________________________",
    "genre": "genre_retro",
    "country": "country_iceland"
  },
  {
    "id": "is156",
    "name": "Vinyl Tónlist Netútvarp",
    "streamUrl": "https://s3.voscast.com:10165/Hljodver",
    "imageUrl": "__________________________",
    "genre": "genre_retro",
    "country": "country_iceland"
  },
  {
    "id": "is157",
    "name": "Jahta",
    "streamUrl": "https://usa7.fastcast4u.com/proxy/mdjscwwh?mp=/1",
    "imageUrl": "__________________________",
    "genre": "genre_pop",
    "country": "country_iceland"
  },
  {
    "id": "is158",
    "name": "X977 radio",
    "streamUrl": "https://live.visir.is/hls-radio/x977/playlist.m3u8",
    "imageUrl": "__________________________",
    "genre": "genre_pop",
    "country": "country_iceland"
  },
  {
    "id": "is159",
    "name": "Reykjavik",
    "streamUrl": "https://stream.zeno.fm/52gf9f8u2ehvv",
    "imageUrl": "__________________________",
    "genre": "genre_pop",
    "country": "country_iceland"
  },
  {
    "id": "is160",
    "name": "Krakka RÚV radio",
    "streamUrl": "http://netradio.ruv.is:80/krakkaruv.aac",
    "imageUrl": "__________________________",
    "genre": "genre_news",
    "country": "country_iceland"
  },
  {
    "id": "is161",
    "name": "K100.5 Kaninn",
    "streamUrl": "http://stream3.radio.is:443/kaninnmobile",
    "imageUrl": "__________________________",
    "genre": "genre_pop",
    "country": "country_iceland"
  },
  {
    "id": "is162",
    "name": "Kiss FM (Reykjavík)",
    "streamUrl": "https://stream.pcradio.ru/kissfm_is-med",
    "imageUrl": "__________________________",
    "genre": "genre_pop",
    "country": "country_iceland"
  },
  {
    "id": "is163",
    "name": "GusGus",
    "streamUrl": "https://stream.pcradio.ru/gus_gus-med",
    "imageUrl": "__________________________",
    "genre": "genre_pop",
    "country": "country_iceland"
  },
  {
    "id": "is164",
    "name": "Bylgjan Islenska",
    "streamUrl": "https://live.visir.is/hls-radio/lettbylgjan/playlist.m3u8",
    "imageUrl": "__________________________",
    "genre": "genre_pop",
    "country": "country_iceland"
  },
  {
    "id": "is165",
    "name": "Utvarp Kantrybaer",
    "streamUrl": "http://93.95.74.162:8000",
    "imageUrl": "__________________________",
    "genre": "genre_folk",
    "country": "country_iceland"
  },
  {
    "id": "is166",
    "name": "Flass 104.5",
    "streamUrl": "http://radio.is:443/flass?type=.mp3",
    "imageUrl": "__________________________",
    "genre": "genre_pop",
    "country": "country_iceland"
  },
  {
    "id": "is167",
    "name": "RUV Rondo",
    "streamUrl": "http://netradio.ruv.is/rondo.mp3",
    "imageUrl": "__________________________",
    "genre": "genre_clasic",
    "country": "country_iceland"
  },
  {
    "id": "is168",
    "name": "Krakka RUV",
    "streamUrl": "http://netradio.ruv.is/krakkaruv.aac",
    "imageUrl": "__________________________",
    "genre": "genre_news",
    "country": "country_iceland"
  },
  {
    "id": "is169",
    "name": "Eve-Radio",
    "streamUrl": "http://media01.gamingnow.net:8000/erweb.mp3",
    "imageUrl": "__________________________",
    "genre": "genre_pop",
    "country": "country_iceland"
  },
  {
    "id": "is170",
    "name": "kyak106",
    "streamUrl": "https://streamingv2.shoutcast.com/kyak106",
    "imageUrl": "__________________________",
    "genre": "genre_pop",
    "country": "country_iceland"
  },
  {
    "id": "is171",
    "name": "FM Trölli",
    "streamUrl": "https://hb.trolli.is/",
    "imageUrl": "__________________________",
    "genre": "genre_pop",
    "country": "country_iceland"
  },
  {
    "id": "is172",
    "name": "105.5 THE HIITZ",
    "streamUrl": "https://stream.zeno.fm/a9ydz10hsxltv",
    "imageUrl": "__________________________",
    "genre": "genre_pop",
    "country": "country_iceland"
  },
  {
    "id": "is173",
    "name": "Bylgjan 80s",
    "streamUrl": "https://live.visir.is/hls-radio/80s/playlist.m3u8",
    "imageUrl": "__________________________",
    "genre": "genre_retro",
    "country": "country_iceland"
  }
]
